ranking_aggregation/__init__.py
ranking_aggregation/benchmark_kemeny.py
ranking_aggregation/preferences/__init__.py
ranking_aggregation/preferences/lehmer.py
ranking_aggregation/preferences/outranking_matrix.py
ranking_aggregation/preferences/profiles.py
ranking_aggregation/preferences/ranking.py
ranking_aggregation/preferences/scores.py
ranking_aggregation/preferences/smith.py
ranking_aggregation/ranking_rules/__init__.py
ranking_aggregation/ranking_rules/condorcet.py
ranking_aggregation/ranking_rules/kemeny.py
ranking_aggregation/ranking_rules/scoring.py
ranking_aggregation-0.0.2.dist-info/LICENSE
ranking_aggregation-0.0.2.dist-info/METADATA
ranking_aggregation-0.0.2.dist-info/WHEEL
ranking_aggregation-0.0.2.dist-info/top_level.txt
ranking_aggregation-0.0.2.dist-info/RECORD
