Metadata-Version: 2.1
Name: ranking_aggregation
Version: 0.0.2
Summary: Ranking aggregation
Home-page: https://www.noeliarico.dev
Author: Noelia Rico,
Author-email: noeliarico@uniovi.es
Project-URL: Bug Tracker, https://www.noeliarico.dev
Classifier: Programming Language :: Python :: 3
Classifier: Operating System :: OS Independent
Requires-Python: >=3.6
License-File: LICENSE
